linking_information_queries/__init__.py
linking_information_queries/dbpedia.py
linking_information_queries/helpers.py
linking_information_queries/information_linking_apis.py
linking_information_queries/information_linking_orcid.py
linking_information_queries/orcid.py
linking_information_queries/wikidata.py
linking_information_queries/wikipedia.py
linking_information_queries-0.1.2.dist-info/METADATA
linking_information_queries-0.1.2.dist-info/WHEEL
linking_information_queries-0.1.2.dist-info/top_level.txt
linking_information_queries-0.1.2.dist-info/RECORD
